mlx/__main__.py
mlx/_reprlib_fix.py
mlx/extension.py
mlx/py.typed
mlx/utils.py
mlx/include/metal_cpp/LICENSE.txt
mlx/include/metal_cpp/README.md
mlx/include/metal_cpp/Foundation/Foundation.hpp
mlx/include/metal_cpp/Foundation/NSArray.hpp
mlx/include/metal_cpp/Foundation/NSAutoreleasePool.hpp
mlx/include/metal_cpp/Foundation/NSBundle.hpp
mlx/include/metal_cpp/Foundation/NSData.hpp
mlx/include/metal_cpp/Foundation/NSDate.hpp
mlx/include/metal_cpp/Foundation/NSDefines.hpp
mlx/include/metal_cpp/Foundation/NSDictionary.hpp
mlx/include/metal_cpp/Foundation/NSEnumerator.hpp
mlx/include/metal_cpp/Foundation/NSError.hpp
mlx/include/metal_cpp/Foundation/NSLock.hpp
mlx/include/metal_cpp/Foundation/NSNotification.hpp
mlx/include/metal_cpp/Foundation/NSNumber.hpp
mlx/include/metal_cpp/Foundation/NSObjCRuntime.hpp
mlx/include/metal_cpp/Foundation/NSObject.hpp
mlx/include/metal_cpp/Foundation/NSPrivate.hpp
mlx/include/metal_cpp/Foundation/NSProcessInfo.hpp
mlx/include/metal_cpp/Foundation/NSRange.hpp
mlx/include/metal_cpp/Foundation/NSSet.hpp
mlx/include/metal_cpp/Foundation/NSSharedPtr.hpp
mlx/include/metal_cpp/Foundation/NSString.hpp
mlx/include/metal_cpp/Foundation/NSTypes.hpp
mlx/include/metal_cpp/Foundation/NSURL.hpp
mlx/include/metal_cpp/Metal/MTL4AccelerationStructure.hpp
mlx/include/metal_cpp/Metal/MTL4Archive.hpp
mlx/include/metal_cpp/Metal/MTL4ArgumentTable.hpp
mlx/include/metal_cpp/Metal/MTL4BinaryFunction.hpp
mlx/include/metal_cpp/Metal/MTL4BinaryFunctionDescriptor.hpp
mlx/include/metal_cpp/Metal/MTL4CommandAllocator.hpp
mlx/include/metal_cpp/Metal/MTL4CommandBuffer.hpp
mlx/include/metal_cpp/Metal/MTL4CommandEncoder.hpp
mlx/include/metal_cpp/Metal/MTL4CommandQueue.hpp
mlx/include/metal_cpp/Metal/MTL4CommitFeedback.hpp
mlx/include/metal_cpp/Metal/MTL4Compiler.hpp
mlx/include/metal_cpp/Metal/MTL4CompilerTask.hpp
mlx/include/metal_cpp/Metal/MTL4ComputeCommandEncoder.hpp
mlx/include/metal_cpp/Metal/MTL4ComputePipeline.hpp
mlx/include/metal_cpp/Metal/MTL4Counters.hpp
mlx_metal-0.30.1.dist-info/licenses/LICENSE
mlx_metal-0.30.1.dist-info/METADATA
mlx_metal-0.30.1.dist-info/WHEEL
mlx_metal-0.30.1.dist-info/top_level.txt
mlx_metal-0.30.1.dist-info/RECORD
